uaimodal/__init__.py
uaimodal/deploy.py
uaimodal/utils.py
uaimodal/api/__init__.py
uaimodal/api/firebase.py
uaimodal/api/job.py
uaimodal-1.0.6.14.dist-info/METADATA
uaimodal-1.0.6.14.dist-info/WHEEL
uaimodal-1.0.6.14.dist-info/top_level.txt
uaimodal-1.0.6.14.dist-info/RECORD
