Metadata-Version: 2.1
Name: uaimodal
Version: 1.0.6.14
Summary: uaimodal
Home-page: https://github.com/vltmedia/uaimodal
Author: Justin Jaro
Author-email: info@uai.contact
License: MIT
Platform: UNKNOWN
Requires-Dist: modal
